blueetl/__init__.py
blueetl/_version.py
blueetl/analysis.py
blueetl/cache.py
blueetl/constants.py
blueetl/features.py
blueetl/parallel.py
blueetl/repository.py
blueetl/resolver.py
blueetl/types.py
blueetl/utils.py
blueetl/validation.py
blueetl/adapters/__init__.py
blueetl/adapters/base.py
blueetl/adapters/circuit.py
blueetl/adapters/node_sets.py
blueetl/adapters/simulation.py
blueetl/adapters/impl/__init__.py
blueetl/adapters/impl/bluepy/__init__.py
blueetl/adapters/impl/bluepy/circuit.py
blueetl/adapters/impl/bluepy/simulation.py
blueetl/adapters/impl/bluepysnap/__init__.py
blueetl/adapters/impl/bluepysnap/circuit.py
blueetl/adapters/impl/bluepysnap/node_sets.py
blueetl/adapters/impl/bluepysnap/simulation.py
blueetl/adapters/interfaces/__init__.py
blueetl/adapters/interfaces/circuit.py
blueetl/adapters/interfaces/node_sets.py
blueetl/adapters/interfaces/simulation.py
blueetl/apps/__init__.py
blueetl/apps/convert.py
blueetl/apps/main.py
blueetl/apps/migrate.py
blueetl/apps/run.py
blueetl/apps/validate.py
blueetl/campaign/__init__.py
blueetl/campaign/config.py
blueetl/campaign/utils.py
blueetl/config/__init__.py
blueetl/config/analysis.py
blueetl/config/analysis_model.py
blueetl/converters/__init__.py
blueetl/converters/convert_spikes.py
blueetl/external/__init__.py
blueetl/external/bluecv/__init__.py
blueetl/external/bluecv/comparison.py
blueetl/external/bluecv/gid.py
blueetl/external/bluecv/neuron_class.py
blueetl/external/bluecv/utils.py
blueetl/external/bnac/__init__.py
blueetl/external/bnac/calculate_features.py
blueetl/external/bnac/calculate_trial_step.py
blueetl/external/soma/__init__.py
blueetl/external/soma/calculate_features.py
blueetl/extract/__init__.py
blueetl/extract/base.py
blueetl/extract/compartment_report.py
blueetl/extract/feature.py
blueetl/extract/neuron_classes.py
blueetl/extract/neurons.py
blueetl/extract/report.py
blueetl/extract/simulations.py
blueetl/extract/soma_report.py
blueetl/extract/spikes.py
blueetl/extract/windows.py
blueetl-0.13.4.dist-info/AUTHORS.txt
blueetl-0.13.4.dist-info/LICENSE.txt
blueetl-0.13.4.dist-info/METADATA
blueetl-0.13.4.dist-info/WHEEL
blueetl-0.13.4.dist-info/entry_points.txt
blueetl-0.13.4.dist-info/top_level.txt
blueetl-0.13.4.dist-info/RECORD
