Metadata-Version: 2.1
Name: blueetl
Version: 0.13.4
Summary: Multiple simulations analysis tool
Author: Blue Brain Project, EPFL
License: Apache-2.0
Project-URL: Homepage, https://github.com/BlueBrain/blueetl
Project-URL: Repository, https://github.com/BlueBrain/blueetl.git
Project-URL: Documentation, https://blueetl.readthedocs.io/
Project-URL: Tracker, https://github.com/BlueBrain/blueetl/issues
Classifier: Development Status :: 2 - Pre-Alpha
Classifier: Intended Audience :: Education
Classifier: Intended Audience :: Science/Research
Classifier: Programming Language :: Python
Classifier: Programming Language :: Python :: 3
Classifier: Programming Language :: Python :: 3.9
Classifier: Programming Language :: Python :: 3.10
Classifier: Programming Language :: Python :: 3.11
Classifier: Programming Language :: Python :: 3.12
Classifier: Topic :: Scientific/Engineering :: Bio-Informatics
Requires-Python: >=3.9
License-File: LICENSE.txt
License-File: AUTHORS.txt
Requires-Dist: blueetl-core>=0.2.3
Requires-Dist: bluepysnap>=1.0.7
Requires-Dist: click>=8
Requires-Dist: jsonschema>=4.0
Requires-Dist: libsonata!=0.1.25; platform_system == "Darwin"
Requires-Dist: numpy>=1.19.4
Requires-Dist: pandas>=1.3.0
Requires-Dist: pyarrow>=7
Requires-Dist: pydantic>=2
Requires-Dist: pyyaml>=5.4.1
Requires-Dist: xarray>=0.18.0
Provides-Extra: extra
Requires-Dist: tables>=3.6.1; extra == "extra"
Provides-Extra: external
Requires-Dist: elephant>=1.1.0; extra == "external"
Requires-Dist: matplotlib>=3.4.3; extra == "external"
Requires-Dist: neo<0.13.4; extra == "external"
Requires-Dist: quantities>=0.13.0; extra == "external"
Requires-Dist: scipy>=1.8.0; extra == "external"
Requires-Dist: seaborn>=0.11.2; extra == "external"
Provides-Extra: docs
Requires-Dist: sphinx; extra == "docs"
Requires-Dist: sphinx-bluebrain-theme; extra == "docs"
Requires-Dist: sphinx-jsonschema; extra == "docs"
Requires-Dist: sphinxcontrib-programoutput; extra == "docs"
Requires-Dist: myst-nb; extra == "docs"
Provides-Extra: all
Requires-Dist: blueetl[external,extra]; extra == "all"
